MANIFEST.in
requirements.txt
setup.py
bin/mendel
fabric_mendel.egg-info/PKG-INFO
fabric_mendel.egg-info/SOURCES.txt
fabric_mendel.egg-info/dependency_links.txt
fabric_mendel.egg-info/not-zip-safe
fabric_mendel.egg-info/requires.txt
fabric_mendel.egg-info/top_level.txt
mendel/__init__.py
mendel/conf.py
mendel/core.py
mendel/fabfile.py
mendel/util.py
mendel/version.py