Metadata-Version: 1.0
Name: fabric-mendel
Version: 0.6.2
Summary: Fabric Tooling for deploying services
Home-page: https://github.com/sproutsocial/mendel
Author: Sprout Social, Inc.
Author-email: UNKNOWN
License: MIT
Platform: UNKNOWN
